README.rst
setup.py
scikit_sos.egg-info/PKG-INFO
scikit_sos.egg-info/SOURCES.txt
scikit_sos.egg-info/dependency_links.txt
scikit_sos.egg-info/entry_points.txt
scikit_sos.egg-info/not-zip-safe
scikit_sos.egg-info/requires.txt
scikit_sos.egg-info/top_level.txt
sksos/__init__.py
sksos/cli.py
sksos/sos.py