Metadata-Version: 1.0
Name: scikit-sos
Version: 0.1.10
Summary: A scikit-learn compatible implementation of Stochastic Outlier Selection (SOS) for detecting outliers.
Home-page: https://github.com/jeroenjanssens/scikit-sos
Author: Jeroen Janssens
Author-email: jeroen@jeroenjanssens.com
License: BSD
Platform: UNKNOWN
